<?xml version="1.0" encoding="utf-8"?>
<Catalog>
    <CWater id="Agria">
        <State index="0">
            <Height value="9.850000"/>
            <Color value="0.098039,0.349020,0.498039,0.300000"/>
            <SpecularScaler value="0.000000"/>
            <UvRate value="-0.046952,0.002132,0.000000,0.000000"/>
            <UvRotate value="4.595277"/>
            <MeshRoughness value="0.408000"/>
            <TextureRoughness value="0.244000"/>
            <RefractionDistortion value="0.020000"/>
        </State>
    </CWater>
    <CWater id="ZerusPool">
        <State index="0">
            <Height value="7.800000"/>
            <Color value="0.470588,0.776471,0.643137,0.000000"/>
            <ColorFallOff value="0.241000"/>
            <SpecularScaler value="0.080000"/>
        </State>
    </CWater>
</Catalog>
