<Catalog>
    <CUnit id="AlliedAircraftCarrier" parent="AlliedVehicle">
        <LifeStart value="500"/>
        <LifeMax value="500"/>
        <Sight value="11"/>
        <CostResource index="Minerals" value="100"/>
        <SubgroupPriority value="840"/>
        <GlossaryPriority value="840"/>
    </CUnit>
    <CModel id="AlliedAircraftCarrier" parent="AlliedVehicle" model="AircraftCarrier"/>
    <CActorUnit id="AlliedAircraftCarrier" parent="AlliedVehicle" unitName="AlliedAircraftCarrier" icon="AircraftCarrier"/>
</Catalog>